money/__init__.py
money/currency.py
money/money.py
mooney-0.0.1.dist-info/LICENSE
mooney-0.0.1.dist-info/METADATA
mooney-0.0.1.dist-info/WHEEL
mooney-0.0.1.dist-info/top_level.txt
mooney-0.0.1.dist-info/RECORD
