Metadata-Version: 2.1
Name: mooney
Version: 0.0.1
Summary: Money & currency abstraction
Home-page: https://github.com/gzg/money
Author: Ekin Öcalan
Author-email: ekin@hey.com
License: UNKNOWN
Project-URL: Bug Tracker, https://github.com/gzg/money/issues
Platform: UNKNOWN
Classifier: Programming Language :: Python :: 3
Classifier: License :: OSI Approved :: MIT License
Classifier: Operating System :: OS Independent
Requires-Python: >=3.6
License-File: LICENSE
